[
    {
      "id": "edulink",
      "title": "Edulink",
      "date": "May 2023 - May 2023",
      "description": "A platform for parents to connect with teachers...",
      "tools": ["React Native", "Node.js", "Fastify", "PostgreSQL"],
      "images": ["../Pictures/Bookit_mods_homepage_02.png", "../Pictures/computer-typing.png"]

    },
    {
      "id": "project2",
      "title": "Another Project",
      "date": "June 2023",
      "description": "Description of another project...",
      "tools": ["React", "Express", "MongoDB"],
      "images": ["/images/project2.png"]
    }
  ]
  